pydmmo/__init__.py
pydmmo-0.1.0.dist-info/METADATA
pydmmo-0.1.0.dist-info/WHEEL
pydmmo-0.1.0.dist-info/licenses/LICENSE
pydmmo-0.1.0.dist-info/RECORD
